h2bb2h/__init__.py
h2bb2h/h2bb2h.py
h2bb2h-0.1.dist-info/METADATA
h2bb2h-0.1.dist-info/WHEEL
h2bb2h-0.1.dist-info/top_level.txt
h2bb2h-0.1.dist-info/RECORD
