Metadata-Version: 2.1
Name: h2bb2h
Version: 0.1
Summary: Human to Byte , Byte to Human
Home-page: https://github.com/Samarth-Tripathi/h2bb2h
Author: Samarth Tripathi
Author-email: samarthtripathi@gmail.com
License: UNKNOWN
Platform: UNKNOWN
